{"cameraMode":{"drawMode":0,"name":"Shaded","section":"Shading Mode"},"sceneLighting":false,"audioPlay":false,"sceneViewState":{"m_AlwaysRefresh":false,"showFog":true,"showSkybox":false,"showFlares":true,"showImageEffects":true,"showParticleSystems":true,"showVisualEffectGraphs":true,"m_FxEnabled":true},"in2DMode":false,"pivot":{"x":-2.384185791015625e-7,"y":0.9333306550979614,"z":-0.0437169075012207},"rotation":{"x":0.20053277909755708,"y":0.2710461914539337,"z":-0.05797363817691803,"w":0.939558744430542},"size":2.4613194465637209,"orthographic":false}